[
  {
    "id": "MRPL.NS",
    "name": "MRPL",
    "ticker": "MRPL",
    "sector": "Energy",
    "cmp": 154.9,
    "pe": 14.1,
    "roe": 14.2,
    "debtEq": 1.08,
    "rsi": "N/A",
    "dma200": 161.46,
    "dma50": 166.37,
    "volSurge": 0.7,
    "dist50dma": -6.9,
    "low52": 120.4,
    "high52": 212.31,
    "upsideLT": 331.7,
    "ltTarget": 668.69,
    "ltAction": "AVOID",
    "stAction": "WATCH",
    "stScore": 0,
    "stReasoning": "Weak structure / Lack of momentum.",
    "news": "News feed unavailable.",
    "avoidReason": "Downtrend (Below 200 DMA)",
    "risk": "CONSERVATIVE",
    "stopLoss": 139.41,
    "reasoning": "Solid fundamentals but lacks extreme asymmetry."
  },
  {
    "id": "CREDITACC.NS",
    "name": "CREDITACCESS GRAMEEN LTD",
    "ticker": "CREDITACC",
    "sector": "Financial Services",
    "cmp": 1264.0,
    "pe": 149.2,
    "roe": 10.5,
    "debtEq": 3.03,
    "rsi": "N/A",
    "dma200": 1307.02,
    "dma50": 1282.04,
    "volSurge": 0.67,
    "dist50dma": -1.4,
    "low52": 1099.7,
    "high52": 1568.0,
    "upsideLT": 104.8,
    "ltTarget": 2588.45,
    "ltAction": "AVOID",
    "stAction": "WATCH",
    "stScore": 15,
    "stReasoning": "Consolidating near 50 DMA support.",
    "news": "News feed unavailable.",
    "avoidReason": "High Debt Risk (D/E > 1.5) \u2022 Downtrend (Below 200 DMA)",
    "risk": "CONSERVATIVE",
    "stopLoss": 1137.6,
    "reasoning": "Solid fundamentals but lacks extreme asymmetry."
  },
  {
    "id": "TATASTEEL.NS",
    "name": "TATA STEEL LIMITED",
    "ticker": "TATASTEEL",
    "sector": "Basic Materials",
    "cmp": 206.77,
    "pe": 23.9,
    "roe": 11.2,
    "debtEq": 0.89,
    "rsi": "N/A",
    "dma200": 187.94,
    "dma50": 208.46,
    "volSurge": 1.19,
    "dist50dma": -0.8,
    "low52": 149.8,
    "high52": 224.4,
    "upsideLT": 102.9,
    "ltTarget": 419.5,
    "ltAction": "BUY",
    "stAction": "WATCH",
    "stScore": 30,
    "stReasoning": "Consolidating near 50 DMA support. Confirmed long-term uptrend.",
    "news": "News feed unavailable.",
    "avoidReason": "None",
    "risk": "CONSERVATIVE",
    "stopLoss": 186.09,
    "reasoning": "Solid fundamentals but lacks extreme asymmetry."
  },
  {
    "id": "IIFL.NS",
    "name": "IIFL FINANCE LIMITED",
    "ticker": "IIFL",
    "sector": "Financial Services",
    "cmp": 516.9,
    "pe": 13.3,
    "roe": 12.3,
    "debtEq": 4.46,
    "rsi": "N/A",
    "dma200": 505.84,
    "dma50": 455.98,
    "volSurge": 0.62,
    "dist50dma": 13.4,
    "low52": 409.1,
    "high52": 675.0,
    "upsideLT": 78.2,
    "ltTarget": 921.27,
    "ltAction": "AVOID",
    "stAction": "MOMENTUM",
    "stScore": 40,
    "stReasoning": "Trading above 50 DMA trend. Confirmed long-term uptrend.",
    "news": "News feed unavailable.",
    "avoidReason": "High Debt Risk (D/E > 1.5)",
    "risk": "CONSERVATIVE",
    "stopLoss": 465.21,
    "reasoning": "Solid fundamentals but lacks extreme asymmetry."
  },
  {
    "id": "TEAMLEASE.NS",
    "name": "TEAMLEASE SERVICES LTD.",
    "ticker": "TEAMLEASE",
    "sector": "Industrials",
    "cmp": 1385.3,
    "pe": 417.3,
    "roe": 14.3,
    "debtEq": 0.11,
    "rsi": "N/A",
    "dma200": 1507.49,
    "dma50": 1278.22,
    "volSurge": 0.42,
    "dist50dma": 8.4,
    "low52": 1065.2,
    "high52": 2138.0,
    "upsideLT": 77.5,
    "ltTarget": 2458.82,
    "ltAction": "AVOID",
    "stAction": "WATCH",
    "stScore": 25,
    "stReasoning": "Trading above 50 DMA trend.",
    "news": "News feed unavailable.",
    "avoidReason": "Downtrend (Below 200 DMA)",
    "risk": "CONSERVATIVE",
    "stopLoss": 1246.77,
    "reasoning": "Virtually debt-free balance sheet."
  },
  {
    "id": "HINDALCO.NS",
    "name": "HINDALCO  INDUSTRIES  LTD",
    "ticker": "HINDALCO",
    "sector": "Basic Materials",
    "cmp": 1092.6,
    "pe": 18.1,
    "roe": 10.3,
    "debtEq": 0.73,
    "rsi": "N/A",
    "dma200": 896.17,
    "dma50": 1030.98,
    "volSurge": 0.69,
    "dist50dma": 6.0,
    "low52": 633.5,
    "high52": 1176.0,
    "upsideLT": 77.2,
    "ltTarget": 1936.14,
    "ltAction": "BUY",
    "stAction": "MOMENTUM",
    "stScore": 40,
    "stReasoning": "Trading above 50 DMA trend. Confirmed long-term uptrend.",
    "news": "News feed unavailable.",
    "avoidReason": "None",
    "risk": "BALANCED",
    "stopLoss": 983.34,
    "reasoning": "Solid fundamentals but lacks extreme asymmetry."
  },
  {
    "id": "GUJGASLTD.NS",
    "name": "GUJARAT GAS LIMITED",
    "ticker": "GUJGASLTD",
    "sector": "Utilities",
    "cmp": 400.5,
    "pe": 1251.6,
    "roe": 12.3,
    "debtEq": 1.19,
    "rsi": "N/A",
    "dma200": 398.12,
    "dma50": 360.9,
    "volSurge": 0.4,
    "dist50dma": 11.0,
    "low52": 301.5,
    "high52": 508.7,
    "upsideLT": 70.9,
    "ltTarget": 684.31,
    "ltAction": "BUY",
    "stAction": "MOMENTUM",
    "stScore": 40,
    "stReasoning": "Trading above 50 DMA trend. Confirmed long-term uptrend.",
    "news": "News feed unavailable.",
    "avoidReason": "None",
    "risk": "BALANCED",
    "stopLoss": 360.45,
    "reasoning": "Solid fundamentals but lacks extreme asymmetry."
  },
  {
    "id": "CHENNPETRO.NS",
    "name": "CHENNAI PETROLEUM CORP LT",
    "ticker": "CHENNPETRO",
    "sector": "Energy",
    "cmp": 1181.4,
    "pe": 5.7,
    "roe": 32.1,
    "debtEq": 0.18,
    "rsi": "N/A",
    "dma200": 910.7,
    "dma50": 1032.63,
    "volSurge": 0.96,
    "dist50dma": 14.4,
    "low52": 603.1,
    "high52": 1225.0,
    "upsideLT": 68.5,
    "ltTarget": 1990.35,
    "ltAction": "BUY",
    "stAction": "MOMENTUM",
    "stScore": 40,
    "stReasoning": "Trading above 50 DMA trend. Confirmed long-term uptrend.",
    "news": "News feed unavailable.",
    "avoidReason": "None",
    "risk": "CONSERVATIVE",
    "stopLoss": 1063.26,
    "reasoning": "Elite capital efficiency (ROE 32.1%)."
  },
  {
    "id": "KEC.NS",
    "name": "KEC INTL. LIMITED",
    "ticker": "KEC",
    "sector": "Industrials",
    "cmp": 497.1,
    "pe": 21.8,
    "roe": 10.5,
    "debtEq": 0.87,
    "rsi": "N/A",
    "dma200": 677.84,
    "dma50": 543.59,
    "volSurge": 0.68,
    "dist50dma": -8.6,
    "low52": 466.0,
    "high52": 947.0,
    "upsideLT": 67.4,
    "ltTarget": 831.94,
    "ltAction": "AVOID",
    "stAction": "WATCH",
    "stScore": 0,
    "stReasoning": "Weak structure / Lack of momentum.",
    "news": "News feed unavailable.",
    "avoidReason": "Downtrend (Below 200 DMA)",
    "risk": "CONSERVATIVE",
    "stopLoss": 447.39,
    "reasoning": "Solid fundamentals but lacks extreme asymmetry."
  },
  {
    "id": "JKPAPER.NS",
    "name": "JK PAPER LIMITED",
    "ticker": "JKPAPER",
    "sector": "Basic Materials",
    "cmp": 359.8,
    "pe": 24.6,
    "roe": 4.8,
    "debtEq": 0.45,
    "rsi": "N/A",
    "dma200": 365.29,
    "dma50": 363.86,
    "volSurge": 0.53,
    "dist50dma": -1.1,
    "low52": 304.85,
    "high52": 444.8,
    "upsideLT": 62.9,
    "ltTarget": 586.15,
    "ltAction": "AVOID",
    "stAction": "WATCH",
    "stScore": 15,
    "stReasoning": "Consolidating near 50 DMA support.",
    "news": "News feed unavailable.",
    "avoidReason": "Low Capital Efficiency (ROE < 8%) \u2022 Downtrend (Below 200 DMA)",
    "risk": "CONSERVATIVE",
    "stopLoss": 323.82,
    "reasoning": "Solid fundamentals but lacks extreme asymmetry."
  },
  {
    "id": "ROUTE.NS",
    "name": "ROUTE MOBILE LIMITED",
    "ticker": "ROUTE",
    "sector": "Communication Services",
    "cmp": 525.45,
    "pe": 13.8,
    "roe": 9.7,
    "debtEq": 0.01,
    "rsi": "N/A",
    "dma200": 630.86,
    "dma50": 504.57,
    "volSurge": 0.32,
    "dist50dma": 4.1,
    "low52": 410.7,
    "high52": 1158.0,
    "upsideLT": 62.6,
    "ltTarget": 854.48,
    "ltAction": "AVOID",
    "stAction": "WATCH",
    "stScore": 25,
    "stReasoning": "Trading above 50 DMA trend.",
    "news": "News feed unavailable.",
    "avoidReason": "Downtrend (Below 200 DMA)",
    "risk": "CONSERVATIVE",
    "stopLoss": 472.91,
    "reasoning": "Virtually debt-free balance sheet."
  },
  {
    "id": "BRIGADE.NS",
    "name": "BRIGADE ENTER. LTD",
    "ticker": "BRIGADE",
    "sector": "Real Estate",
    "cmp": 651.4,
    "pe": 2505.4,
    "roe": 10.8,
    "debtEq": 0.84,
    "rsi": "N/A",
    "dma200": 821.81,
    "dma50": 719.0,
    "volSurge": 1.32,
    "dist50dma": -9.4,
    "low52": 601.0,
    "high52": 1332.0,
    "upsideLT": 61.4,
    "ltTarget": 1051.44,
    "ltAction": "AVOID",
    "stAction": "WATCH",
    "stScore": 25,
    "stReasoning": "Heavy Volume Accumulation (1.32x Avg).",
    "news": "News feed unavailable.",
    "avoidReason": "Downtrend (Below 200 DMA)",
    "risk": "CONSERVATIVE",
    "stopLoss": 586.26,
    "reasoning": "Solid fundamentals but lacks extreme asymmetry."
  },
  {
    "id": "LT.NS",
    "name": "LARSEN & TOUBRO LTD.",
    "ticker": "LT",
    "sector": "Industrials",
    "cmp": 3953.2,
    "pe": 33.8,
    "roe": 17.0,
    "debtEq": 0.98,
    "rsi": "N/A",
    "dma200": 3908.6,
    "dma50": 3930.72,
    "volSurge": 0.62,
    "dist50dma": 0.6,
    "low52": 3288.1,
    "high52": 4440.0,
    "upsideLT": 56.8,
    "ltTarget": 6197.32,
    "ltAction": "BUY",
    "stAction": "MOMENTUM",
    "stScore": 40,
    "stReasoning": "Trading above 50 DMA trend. Confirmed long-term uptrend.",
    "news": "News feed unavailable.",
    "avoidReason": "None",
    "risk": "CONSERVATIVE",
    "stopLoss": 3557.88,
    "reasoning": "Solid fundamentals but lacks extreme asymmetry."
  },
  {
    "id": "OIL.NS",
    "name": "OIL INDIA LTD",
    "ticker": "OIL",
    "sector": "Energy",
    "cmp": 483.35,
    "pe": 11.9,
    "roe": 12.7,
    "debtEq": 0.59,
    "rsi": "N/A",
    "dma200": 446.24,
    "dma50": 480.8,
    "volSurge": 0.71,
    "dist50dma": 0.5,
    "low52": 384.6,
    "high52": 531.0,
    "upsideLT": 54.9,
    "ltTarget": 748.76,
    "ltAction": "BUY",
    "stAction": "MOMENTUM",
    "stScore": 40,
    "stReasoning": "Trading above 50 DMA trend. Confirmed long-term uptrend.",
    "news": "News feed unavailable.",
    "avoidReason": "None",
    "risk": "CONSERVATIVE",
    "stopLoss": 435.02,
    "reasoning": "Solid fundamentals but lacks extreme asymmetry."
  },
  {
    "id": "GAIL.NS",
    "name": "GAIL (INDIA) LTD",
    "ticker": "GAIL",
    "sector": "Utilities",
    "cmp": 167.4,
    "pe": 14.5,
    "roe": 8.7,
    "debtEq": 0.28,
    "rsi": "N/A",
    "dma200": 167.3,
    "dma50": 158.03,
    "volSurge": 0.53,
    "dist50dma": 5.9,
    "low52": 134.36,
    "high52": 202.79,
    "upsideLT": 54.8,
    "ltTarget": 259.17,
    "ltAction": "BUY",
    "stAction": "MOMENTUM",
    "stScore": 40,
    "stReasoning": "Trading above 50 DMA trend. Confirmed long-term uptrend.",
    "news": "News feed unavailable.",
    "avoidReason": "None",
    "risk": "CONSERVATIVE",
    "stopLoss": 150.66,
    "reasoning": "Solid fundamentals but lacks extreme asymmetry."
  },
  {
    "id": "CHOLAHLDNG.NS",
    "name": "CHOLAMANDALAM FIN HOL LTD",
    "ticker": "CHOLAHLDNG",
    "sector": "Financial Services",
    "cmp": 1449.0,
    "pe": 11.1,
    "roe": 18.0,
    "debtEq": 6.21,
    "rsi": "N/A",
    "dma200": 1740.38,
    "dma50": 1574.58,
    "volSurge": 0.82,
    "dist50dma": -8.0,
    "low52": 1305.0,
    "high52": 2231.6,
    "upsideLT": 54.6,
    "ltTarget": 2240.72,
    "ltAction": "AVOID",
    "stAction": "WATCH",
    "stScore": 0,
    "stReasoning": "Weak structure / Lack of momentum.",
    "news": "News feed unavailable.",
    "avoidReason": "High Debt Risk (D/E > 1.5) \u2022 Downtrend (Below 200 DMA)",
    "risk": "CONSERVATIVE",
    "stopLoss": 1304.1,
    "reasoning": "Elite capital efficiency (ROE 18.0%)."
  },
  {
    "id": "MOTILALOFS.NS",
    "name": "MOTILAL OSWAL FIN LTD",
    "ticker": "MOTILALOFS",
    "sector": "Financial Services",
    "cmp": 855.35,
    "pe": 26.0,
    "roe": 15.6,
    "debtEq": 1.64,
    "rsi": "N/A",
    "dma200": 848.74,
    "dma50": 800.61,
    "volSurge": 0.62,
    "dist50dma": 6.8,
    "low52": 614.9,
    "high52": 1097.1,
    "upsideLT": 53.8,
    "ltTarget": 1315.29,
    "ltAction": "AVOID",
    "stAction": "MOMENTUM",
    "stScore": 40,
    "stReasoning": "Trading above 50 DMA trend. Confirmed long-term uptrend.",
    "news": "News feed unavailable.",
    "avoidReason": "High Debt Risk (D/E > 1.5)",
    "risk": "CONSERVATIVE",
    "stopLoss": 769.82,
    "reasoning": "Solid fundamentals but lacks extreme asymmetry."
  },
  {
    "id": "ABCAPITAL.NS",
    "name": "ADITYA BIRLA CAPITAL LTD.",
    "ticker": "ABCAPITAL",
    "sector": "Financial Services",
    "cmp": 357.5,
    "pe": 25.1,
    "roe": 11.2,
    "debtEq": 4.92,
    "rsi": "N/A",
    "dma200": 331.43,
    "dma50": 341.37,
    "volSurge": 1.1,
    "dist50dma": 4.7,
    "low52": 222.46,
    "high52": 375.95,
    "upsideLT": 53.3,
    "ltTarget": 548.06,
    "ltAction": "AVOID",
    "stAction": "MOMENTUM",
    "stScore": 40,
    "stReasoning": "Trading above 50 DMA trend. Confirmed long-term uptrend.",
    "news": "News feed unavailable.",
    "avoidReason": "High Debt Risk (D/E > 1.5)",
    "risk": "CONSERVATIVE",
    "stopLoss": 321.75,
    "reasoning": "Solid fundamentals but lacks extreme asymmetry."
  },
  {
    "id": "AXISBANK.NS",
    "name": "AXIS BANK LIMITED",
    "ticker": "AXISBANK",
    "sector": "Financial Services",
    "cmp": 1272.3,
    "pe": 15.1,
    "roe": 13.2,
    "debtEq": "N/A",
    "rsi": "N/A",
    "dma200": 1254.23,
    "dma50": 1282.63,
    "volSurge": 1.02,
    "dist50dma": -0.8,
    "low52": 1042.5,
    "high52": 1418.3,
    "upsideLT": 49.1,
    "ltTarget": 1897.61,
    "ltAction": "BUY",
    "stAction": "WATCH",
    "stScore": 30,
    "stReasoning": "Consolidating near 50 DMA support. Confirmed long-term uptrend.",
    "news": "News feed unavailable.",
    "avoidReason": "None",
    "risk": "CONSERVATIVE",
    "stopLoss": 1145.07,
    "reasoning": "Solid fundamentals but lacks extreme asymmetry."
  },
  {
    "id": "WELCORP.NS",
    "name": "WELSPUN CORP LIMITED",
    "ticker": "WELCORP",
    "sector": "Basic Materials",
    "cmp": 1388.8,
    "pe": 22.7,
    "roe": 18.9,
    "debtEq": 0.25,
    "rsi": "N/A",
    "dma200": 913.05,
    "dma50": 1160.85,
    "volSurge": 0.41,
    "dist50dma": 19.6,
    "low52": 710.0,
    "high52": 1425.0,
    "upsideLT": 47.0,
    "ltTarget": 2041.5,
    "ltAction": "BUY",
    "stAction": "MOMENTUM",
    "stScore": 40,
    "stReasoning": "Trading above 50 DMA trend. Confirmed long-term uptrend.",
    "news": "News feed unavailable.",
    "avoidReason": "None",
    "risk": "CONSERVATIVE",
    "stopLoss": 1249.92,
    "reasoning": "Elite capital efficiency (ROE 18.9%)."
  }
]